jupyterlab_launcher_navigate_to_kernel_extension/__init__.py
jupyterlab_launcher_navigate_to_kernel_extension/_version.py
jupyterlab_launcher_navigate_to_kernel_extension/handlers.py
jupyterlab_launcher_navigate_to_kernel_extension-1.1.16.data/data/etc/jupyter/jupyter_server_config.d/jupyterlab_launcher_navigate_to_kernel_extension.json
jupyterlab_launcher_navigate_to_kernel_extension-1.1.16.data/data/share/jupyter/labextensions/jupyterlab_launcher_navigate_to_kernel_extension/package.json
jupyterlab_launcher_navigate_to_kernel_extension-1.1.16.data/data/share/jupyter/labextensions/jupyterlab_launcher_navigate_to_kernel_extension/schemas/jupyterlab_launcher_navigate_to_kernel_extension/package.json.orig
jupyterlab_launcher_navigate_to_kernel_extension-1.1.16.data/data/share/jupyter/labextensions/jupyterlab_launcher_navigate_to_kernel_extension/schemas/jupyterlab_launcher_navigate_to_kernel_extension/plugin.json
jupyterlab_launcher_navigate_to_kernel_extension-1.1.16.data/data/share/jupyter/labextensions/jupyterlab_launcher_navigate_to_kernel_extension/static/509.d4ca81fcd1402a29739a.js
jupyterlab_launcher_navigate_to_kernel_extension-1.1.16.data/data/share/jupyter/labextensions/jupyterlab_launcher_navigate_to_kernel_extension/static/728.4b5e89955ce61a9266d6.js
jupyterlab_launcher_navigate_to_kernel_extension-1.1.16.data/data/share/jupyter/labextensions/jupyterlab_launcher_navigate_to_kernel_extension/static/remoteEntry.4ee58419273a3f998ca4.js
jupyterlab_launcher_navigate_to_kernel_extension-1.1.16.data/data/share/jupyter/labextensions/jupyterlab_launcher_navigate_to_kernel_extension/static/style.js
jupyterlab_launcher_navigate_to_kernel_extension-1.1.16.data/data/share/jupyter/labextensions/jupyterlab_launcher_navigate_to_kernel_extension/static/third-party-licenses.json
jupyterlab_launcher_navigate_to_kernel_extension-1.1.16.data/data/share/jupyter/labextensions/jupyterlab_launcher_navigate_to_kernel_extension/install.json
jupyterlab_launcher_navigate_to_kernel_extension-1.1.16.dist-info/METADATA
jupyterlab_launcher_navigate_to_kernel_extension-1.1.16.dist-info/WHEEL
jupyterlab_launcher_navigate_to_kernel_extension-1.1.16.dist-info/licenses/LICENSE
jupyterlab_launcher_navigate_to_kernel_extension-1.1.16.dist-info/RECORD
