Metadata-Version: 2.4
Name: jupyterlab_launcher_navigate_to_kernel_extension
Version: 1.1.16
Summary: Jupyterlab extension to allow user to right-click on the kernel launcher button and select 'Show in File Browser' or 'Open Terminal at location' menus and get them to navigate to location or open location in terminal respectively
Project-URL: Homepage, https://github.com/stellarshenson/jupyterlab_launcher_navigate_to_kernel_extension
Project-URL: Bug Tracker, https://github.com/stellarshenson/jupyterlab_launcher_navigate_to_kernel_extension/issues
Project-URL: Repository, https://github.com/stellarshenson/jupyterlab_launcher_navigate_to_kernel_extension.git
Author-email: Stellars Henson <konrad.jelen@gmail.com>
License: BSD 3-Clause License
License-File: LICENSE
Keywords: jupyter,jupyterlab,jupyterlab-extension
Classifier: Framework :: Jupyter
Classifier: Framework :: Jupyter :: JupyterLab
Classifier: Framework :: Jupyter :: JupyterLab :: 4
Classifier: Framework :: Jupyter :: JupyterLab :: Extensions
Classifier: Framework :: Jupyter :: JupyterLab :: Extensions :: Prebuilt
Classifier: License :: OSI Approved :: BSD License
Classifier: Programming Language :: Python
Classifier: Programming Language :: Python :: 3
Classifier: Programming Language :: Python :: 3.10
Classifier: Programming Language :: Python :: 3.11
Classifier: Programming Language :: Python :: 3.12
Classifier: Programming Language :: Python :: 3.13
Classifier: Programming Language :: Python :: 3.14
Requires-Python: >=3.10
Requires-Dist: jupyter-client>=8.0.0
Requires-Dist: jupyter-server>=2.0.0
